ivoox_client/__init__.py
ivoox_client/helpers.py
ivoox_client/ivoox.py
ivoox_client-0.0.1.dist-info/METADATA
ivoox_client-0.0.1.dist-info/WHEEL
ivoox_client-0.0.1.dist-info/top_level.txt
ivoox_client-0.0.1.dist-info/RECORD
